LICENSE.txt
MANIFEST.in
README.rst
setup.py
pyconizr/__init__.py
pyconizr/helpers.py
pyconizr/iconizr.py
pyconizr/options.py
pyconizr/run.py
pyconizr/version.py
pyconizr.egg-info/PKG-INFO
pyconizr.egg-info/SOURCES.txt
pyconizr.egg-info/dependency_links.txt
pyconizr.egg-info/entry_points.txt
pyconizr.egg-info/requires.txt
pyconizr.egg-info/top_level.txt
pyconizr/img/__init__.py
pyconizr/img/base.py
pyconizr/img/png.py
pyconizr/img/svg.py