Metadata-Version: 1.1
Name: pyconizr
Version: 0.1b2
Summary: Generate sprites from SVG icons
Home-page: https://bitbucket.org/tkhyn/pyconizr/
Author: Thomas Khyn
Author-email: thomas@ksytek.com
License: UNKNOWN
Keywords: iconizr,SVG,PNG,sprite
Platform: UNKNOWN
Classifier: Programming Language :: Python :: 2.6
Classifier: Programming Language :: Python :: 2.7
Classifier: License :: OSI Approved :: MIT License
Classifier: Operating System :: OS Independent
Classifier: Development Status :: 4 - Beta
Classifier: Intended Audience :: Developers
Classifier: Environment :: Console
Classifier: Topic :: Multimedia :: Graphics :: Graphics Conversion
Classifier: Topic :: Multimedia :: Graphics :: Editors :: Vector-Based
Classifier: Topic :: Software Development :: Build Tools
